LICENSE
MANIFEST.in
README.rst
requirements.txt
setup.py
tweetmagick/__init__.py
tweetmagick/themes.py
tweetmagick/tweetmagick.py
tweetmagick.egg-info/PKG-INFO
tweetmagick.egg-info/SOURCES.txt
tweetmagick.egg-info/dependency_links.txt
tweetmagick.egg-info/requires.txt
tweetmagick.egg-info/top_level.txt