Metadata-Version: 1.1
Name: tweetmagick
Version: 0.2
Summary: Create images that look like tweets
Home-page: https://github.com/Szero/tweetmagick
Author: Szero
Author-email: singleton@tfwno.gf
License: ISC
Platform: UNKNOWN
Classifier: Intended Audience :: Developers
Classifier: Natural Language :: English
Classifier: License :: OSI Approved :: ISC License (ISCL)
Classifier: Operating System :: Unix
Classifier: Programming Language :: Python
Classifier: Programming Language :: Python :: 3.6
Classifier: Programming Language :: Python :: 3.7
Classifier: Programming Language :: Python :: 3 :: Only
Classifier: Topic :: Software Development :: Libraries :: Python Modules
